mixrpay/__init__.py
mixrpay/agent_wallet.py
mixrpay/exceptions.py
mixrpay/session_key.py
mixrpay/x402.py
mixrpay-0.2.0.dist-info/METADATA
mixrpay-0.2.0.dist-info/WHEEL
mixrpay-0.2.0.dist-info/top_level.txt
mixrpay-0.2.0.dist-info/RECORD
