Metadata-Version: 2.4
Name: mixrpay
Version: 0.2.0
Summary: MixrPay Agent SDK - Enable AI agents to make x402 payments with session keys
Author-email: MixrPay <support@mixrpay.com>
License: MIT
Project-URL: Homepage, https://mixrpay.com
Project-URL: Documentation, https://docs.mixrpay.com/sdk/python
Project-URL: Repository, https://github.com/mixrpay/mixrpay-python
Project-URL: Changelog, https://github.com/mixrpay/mixrpay-python/blob/main/CHANGELOG.md
Keywords: payments,ai-agents,x402,cryptocurrency,usdc,blockchain,web3,langchain,crewai
Classifier: Development Status :: 4 - Beta
Classifier: Intended Audience :: Developers
Classifier: License :: OSI Approved :: MIT License
Classifier: Operating System :: OS Independent
Classifier: Programming Language :: Python :: 3
Classifier: Programming Language :: Python :: 3.9
Classifier: Programming Language :: Python :: 3.10
Classifier: Programming Language :: Python :: 3.11
Classifier: Programming Language :: Python :: 3.12
Classifier: Topic :: Software Development :: Libraries :: Python Modules
Classifier: Topic :: Internet :: WWW/HTTP
Classifier: Topic :: Office/Business :: Financial
Requires-Python: >=3.9
Requires-Dist: httpx>=0.24.0
Requires-Dist: eth-account>=0.9.0
Requires-Dist: pydantic>=2.0
Provides-Extra: dev
Requires-Dist: pytest>=7.0; extra == "dev"
Requires-Dist: pytest-asyncio>=0.21.0; extra == "dev"
Requires-Dist: pytest-cov>=4.0; extra == "dev"
Requires-Dist: black>=23.0; extra == "dev"
Requires-Dist: mypy>=1.0; extra == "dev"
Requires-Dist: ruff>=0.1.0; extra == "dev"
Provides-Extra: langchain
Requires-Dist: langchain>=0.1.0; extra == "langchain"
Requires-Dist: langchain-core>=0.1.0; extra == "langchain"
Provides-Extra: crewai
Requires-Dist: crewai>=0.1.0; extra == "crewai"
Provides-Extra: all
Requires-Dist: mixrpay[crewai,dev,langchain]; extra == "all"
